{
  "_id": "56ba05f5cd0d3c5026605e98",
  "code": "5c4e4e09-fae5-49f0-f0a5-ebc83e80e977",
  "title": "",
  "slug": "56ba05f5cd0d3c5026605e98",
  "date": "2016-02-09T15:31:38.298Z",
  "userquery": {
    "_id": "56b0ea077205fbd00257003b",
    "slug": "test-cities-2",
    "stateindexing": "0000quoted.00000321MY",
    "destinationsindexing": "th.00000321MY",
    "createdonindexing": "201601021740.00000321MY",
    "startdateindexing": "201601080000.00000321MY",
    "title": "TEST CITIES",
    "name": "",
    "code": "000321MY",
    "publishedDate": "2016-02-02T17:40:49.990Z",
    "description": "New Query...",
    "travelercode": null,
    "traveler": null,
    "state": "quoted",
    "affiliate": "569923c3e07e363c19220290",
    "__v": 6,
    "updatedOn": "2016-03-02T08:19:47.314Z",
    "createdOn": "2016-02-02T17:40:23.764Z",
    "passengers": [
      {
        "_id": "56b0ea077205fbd00257003c",
        "acomodattion": {
          "howmany": 2
        }
      }
    ],
    "comments": [],
    "historic": [
      {
        "date": "2016-02-02T17:42:46.408Z",
        "state": "new quote for dmc: ES11",
        "user": "pablo@openmarket.travel",
        "_id": "56b0ea3736020ea80ab4d7f2",
        "mailSend": [
          {
            "name": "dmcnewrequest_en",
            "date": "2016-02-02T17:42:46.408Z",
            "_id": "56b0ea3736020ea80ab4d7f3"
          }
        ]
      },
      {
        "date": "2016-02-02T17:45:22.355Z",
        "state": "NEW quote: QUOTE-ES11X322 is  under review by admin.",
        "user": "pablo@openmarket.travel",
        "_id": "56b0ead436020ea80ab4d7f9",
        "mailSend": [
          {
            "name": "omtgunoca",
            "date": "2016-02-02T17:45:22.355Z",
            "_id": "56b0ead436020ea80ab4d7fa"
          }
        ]
      },
      {
        "date": "2016-02-02T17:45:51.924Z",
        "state": "quote: QUOTE-ES11X322 is  published by admin.",
        "user": "pablo@openmarket.travel",
        "_id": "56b0eaf136020ea80ab4d7fd",
        "mailSend": [
          {
            "name": "usernewquote",
            "date": "2016-02-02T17:45:51.924Z",
            "_id": "56b0eaf136020ea80ab4d7fe"
          }
        ]
      },
      {
        "date": "2016-02-05T16:04:21.900Z",
        "state": "quote: QUOTE-ES11X322 is  published by admin.",
        "user": "pablo@openmarket.travel",
        "_id": "56b4c7a0a6ce45941c6e0d49",
        "mailSend": [
          {
            "name": "usernewquote",
            "date": "2016-02-05T16:04:21.900Z",
            "_id": "56b4c7a0a6ce45941c6e0d4a"
          }
        ]
      },
      {
        "date": "2016-02-11T08:24:09.564Z",
        "state": "quote: QUOTE-ES11X322 is  published by admin.",
        "user": "pablo@openmarket.travel",
        "_id": "56bc44c72906aba83f32cca6",
        "mailSend": [
          {
            "name": "usernewquote",
            "date": "2016-02-11T08:24:09.564Z",
            "_id": "56bc44c72906aba83f32cca7"
          }
        ]
      },
      {
        "date": "2016-03-02T08:21:41.300Z",
        "state": "new quote for dmc: ES553",
        "user": "pablo@openmarket.travel",
        "_id": "56d6a223a86282482f0c5c83",
        "mailSend": [
          {
            "name": "dmcnewrequest_en",
            "date": "2016-03-02T08:21:41.300Z",
            "_id": "56d6a223a86282482f0c5c84"
          }
        ]
      }
    ],
    "roomDistribution": [
      {
        "numRoom": 0,
        "slug": "double0",
        "_id": "56b0ea077205fbd00257003d",
        "paxList": [
          {
            "typePax": "adult",
            "age": 30,
            "holder": true,
            "_id": "56b0ea077205fbd00257003f"
          },
          {
            "typePax": "adult",
            "age": 30,
            "_id": "56b0ea077205fbd00257003e"
          }
        ],
        "roomType": {
          "roomCode": "double",
          "label": "Doble",
          "pax": 2
        }
      }
    ],
    "whattodo": [
      {
        "_id": "543e99a4ee63d0382c52deeb",
        "slug": "beach",
        "label": "Playa",
        "label_en": "Beach"
      }
    ],
    "destinations": [
      {
        "fulladdress": "Chiang Mai, Tailandia",
        "city": "Chiang Mai",
        "country": "Tailandia",
        "countrycode": "TH",
        "longitude": 103.8042382,
        "latitude": 16.2375533,
        "_id": "56b0ea077205fbd002570042"
      },
      {
        "fulladdress": "Chiang Rai, Tailandia",
        "city": "Chiang Rai",
        "country": "Tailandia",
        "countrycode": "TH",
        "longitude": 99.82682760000002,
        "latitude": 19.8892545,
        "_id": "56b0ea077205fbd002570041"
      },
      {
        "fulladdress": "Bangkok, Tailandia",
        "city": "Bangkok",
        "country": "Tailandia",
        "countrycode": "TH",
        "longitude": 100.52412349999997,
        "latitude": 13.7278956,
        "_id": "56b0ea077205fbd002570040"
      }
    ],
    "chats": [],
    "dmcs": [
      "547f280c7584bc040ff2c606",
      "55434f67aaeed2f82b303cfb",
      "547f280c7584bc040ff2c606",
      "55434f67aaeed2f82b303cfb"
    ],
    "quotes": [
      "56d6a223a86282482f0c5c82",
      "56b0ea3736020ea80ab4d7f1",
      "56d6a223a86282482f0c5c82",
      "56b0ea3736020ea80ab4d7f1"
    ],
    "budget": {
      "cost": 450,
      "currency": {
        "label": "Euro",
        "symbol": "€",
        "value": "EUR"
      }
    },
    "hosting": {
      "hostingKindNotes": "",
      "lowcosthotels": true,
      "standarhotels": false,
      "superiorhotels": false,
      "charmhotels": false,
      "luxuryhotels": false
    },
    "dates": {
      "knowingdates": false,
      "arrivaldate": "2016-02-08T00:00:00.000Z",
      "week": "2",
      "alreadygotflights": false,
      "dataflightsIn": "",
      "dataflightsOut": "",
      "duration": "10",
      "flexibility": {
        "number": 0,
        "range": "days"
      },
      "month": {
        "monthnumber": 2,
        "monthname": "Febrero",
        "monthyear": 2016
      },
      "arrival": {
        "year": 2016,
        "month": 1,
        "day": 8,
        "monthname_en": "February",
        "monthname_es": "Febrero"
      }
    },
    "additionalinfo": {
      "description": "",
      "trip": "grouptrip",
      "regimen": "fb",
      "needs": "",
      "guide": {
        "included": false,
        "language": {
          "spanish": false,
          "english": false,
          "french": false,
          "german": false,
          "italian": false,
          "portuguese": false
        }
      }
    }
  },
  "booking": null,
  "quote": {
    "_id": "56b0ea3736020ea80ab4d7f1",
    "slug": "tailandia",
    "createdonindexing": "201601021741.QUOTE-ES11X322",
    "title_en": "Tailandia",
    "title_es": "Tailandia",
    "code": "QUOTE-ES11X322",
    "publishedDate": "2016-02-02T17:41:11.165Z",
    "description": "",
    "name": "tailandia test",
    "userqueryCode": "000321MY",
    "userqueryId": "56b0ea077205fbd00257003b",
    "travelercode": null,
    "dmccode": "ES11",
    "status": "published",
    "__v": 1,
    "operationStartDate": "2016-04-15T22:00:00.000Z",
    "products": "56b0ead336020ea80ab4d7f4",
    "quoteValidDate": "2016-04-29T22:00:00.000Z",
    "comission": 10,
    "isB2C": false,
    "updatedOn": "2016-03-02T08:19:47.169Z",
    "createdOn": "2016-02-02T17:41:11.165Z",
    "pvpAffiliate": {
      "value": 1248,
      "exchange": {
        "value": 1248,
        "currency": {
          "label": "Euro",
          "symbol": "€",
          "value": "EUR"
        }
      },
      "currency": {
        "label": "Euro",
        "symbol": "€",
        "value": "EUR"
      }
    },
    "amount": {
      "value": 1111,
      "exchange": {
        "value": 1111,
        "currency": {
          "label": "Euro",
          "symbol": "€",
          "value": "EUR"
        }
      },
      "currency": {
        "label": "Euro",
        "symbol": "€",
        "value": "EUR"
      }
    },
    "netPrice": {
      "value": 1000,
      "exchange": {
        "value": 1000,
        "currency": {
          "label": "Euro",
          "symbol": "€",
          "value": "EUR"
        }
      },
      "currency": {
        "label": "Euro",
        "symbol": "€",
        "value": "EUR"
      }
    },
    "children": [],
    "rooms": {
      "quad": {
        "quantity": 0,
        "amountPricePerPax": {
          "value": 0,
          "exchange": {
            "value": 0,
            "currency": {
              "label": "",
              "symbol": "",
              "value": ""
            }
          },
          "currency": {
            "label": "Euro",
            "symbol": "€",
            "value": "EUR"
          }
        },
        "pricePerPax": {
          "value": 0,
          "exchange": {
            "value": 0,
            "currency": {
              "label": "",
              "symbol": "",
              "value": ""
            }
          },
          "currency": {
            "label": "Euro",
            "symbol": "€",
            "value": "EUR"
          }
        }
      },
      "triple": {
        "quantity": 0,
        "amountPricePerPax": {
          "value": 0,
          "exchange": {
            "value": 0,
            "currency": {
              "label": "",
              "symbol": "",
              "value": ""
            }
          },
          "currency": {
            "label": "Euro",
            "symbol": "€",
            "value": "EUR"
          }
        },
        "pricePerPax": {
          "value": 0,
          "exchange": {
            "value": 0,
            "currency": {
              "label": "",
              "symbol": "",
              "value": ""
            }
          },
          "currency": {
            "label": "Euro",
            "symbol": "€",
            "value": "EUR"
          }
        }
      },
      "double": {
        "quantity": 0,
        "amountPricePerPax": {
          "value": 0,
          "exchange": {
            "value": 0,
            "currency": {
              "label": "",
              "symbol": "",
              "value": ""
            }
          },
          "currency": {
            "label": "Euro",
            "symbol": "€",
            "value": "EUR"
          }
        },
        "pricePerPax": {
          "value": 0,
          "exchange": {
            "value": 0,
            "currency": {
              "label": "",
              "symbol": "",
              "value": ""
            }
          },
          "currency": {
            "label": "Euro",
            "symbol": "€",
            "value": "EUR"
          }
        }
      },
      "single": {
        "quantity": 1,
        "pvpAffiliatePerPax": {
          "value": 1248,
          "exchange": {
            "value": 1248,
            "currency": {
              "label": "Euro",
              "symbol": "€",
              "value": "EUR"
            }
          },
          "currency": {
            "label": "Euro",
            "symbol": "€",
            "value": "EUR"
          }
        },
        "amountPricePerPax": {
          "value": 1111,
          "exchange": {
            "value": 1111,
            "currency": {
              "label": "Euro",
              "symbol": "€",
              "value": "EUR"
            }
          },
          "currency": {
            "label": "Euro",
            "symbol": "€",
            "value": "EUR"
          }
        },
        "pricePerPax": {
          "value": 1000,
          "exchange": {
            "value": 1000,
            "currency": {
              "label": "Euro",
              "symbol": "€",
              "value": "EUR"
            }
          },
          "currency": {
            "label": "Euro",
            "symbol": "€",
            "value": "EUR"
          }
        }
      }
    },
    "fees": {
      "unique": 10,
      "groups": 12,
      "tailormade": 11,
      "flights": 8
    },
    "quoteValidUntil": {
      "day": 30,
      "month": 3,
      "monthname_en": "April",
      "monthname_es": "Abril",
      "year": 2016
    },
    "operationStart": {
      "day": 16,
      "month": 3,
      "monthname_en": "April",
      "monthname_es": "Abril",
      "year": 2016
    },
    "responseDetails": {
      "comments": "",
      "conditions": "",
      "cancelpolicy": {
        "_es": "33 dias antes de la llegada 50% de gastos sobre el total del viaje\n44 horas antes o no show 100% de gastos sobre el total del viaje",
        "_en": "11 dias antes de la llegada 50% de gastos sobre el total del viaje\n22 horas antes o no show 100% de gastos sobre el total del viaje"
      }
    }
  },
  "traveler": null,
  "dmc": "547f280c7584bc040ff2c606",
  "affiliate": "569923c3e07e363c19220290",
  "__v": 49,
  "updatedOn": "2016-03-02T11:38:53.716Z",
  "createdOn": "2016-02-09T15:29:57.032Z",
  "messages": [
    {
      "message": "cas",
      "date": "2016-02-09T15:31:42.143Z",
      "_id": "56ba05f5cd0d3c5026605e99",
      "from": {
        "type": "affiliate",
        "id": "569923c3e07e363c19220290",
        "name": "Agencia de Test",
        "email": "pablo@yourttoo.com",
        "avatarimg": "http://res.cloudinary.com/openmarket-travel/image/upload/cs_no_cmyk/w_36,h_36,c_fill,g_face,q_90,r_18/hrh92ko7prbyxml4hcat.jpg",
        "status": "read"
      },
      "to": {
        "type": "dmc",
        "id": "547f280c7584bc040ff2c606",
        "name": "Dmc Test Ltd",
        "email": "pableco@gmail.com",
        "avatarimg": "http://res.cloudinary.com/open-market-travel/image/upload/cs_no_cmyk/w_36,h_36,c_fill,g_face,q_90,r_18/kfnorwwnumnxxhk42tv1.png",
        "status": "read"
      }
    },
    {
      "message": "Hola Mensaje desde el AAVV al DMC .... llega a OMT?",
      "date": "2016-02-09T18:02:18.711Z",
      "_id": "56ba2942cd0d3c5026605ee6",
      "from": {
        "type": "affiliate",
        "id": "569923c3e07e363c19220290",
        "name": "Agencia de Test",
        "email": "pablo@yourttoo.com",
        "avatarimg": "http://res.cloudinary.com/openmarket-travel/image/upload/cs_no_cmyk/w_36,h_36,c_fill,g_face,q_90,r_18/hrh92ko7prbyxml4hcat.jpg",
        "status": "read"
      },
      "to": {
        "type": "dmc",
        "id": "547f280c7584bc040ff2c606",
        "name": "Dmc Test Ltd",
        "email": "pableco@gmail.com",
        "avatarimg": "http://res.cloudinary.com/open-market-travel/image/upload/cs_no_cmyk/w_36,h_36,c_fill,g_face,q_90,r_18/kfnorwwnumnxxhk42tv1.png",
        "status": "read"
      }
    },
    {
      "message": "Respuesta del DMC al AAVV llega a OMT?",
      "date": "2016-02-09T18:03:58.940Z",
      "_id": "56ba29a40392112412979ed4",
      "from": {
        "type": "dmc",
        "id": "547f280c7584bc040ff2c606",
        "name": "Dmc Test Ltd",
        "email": "pableco@gmail.com",
        "avatarimg": "http://res.cloudinary.com/open-market-travel/image/upload/cs_no_cmyk/w_36,h_36,c_fill,g_face,q_90,r_18/kfnorwwnumnxxhk42tv1.png",
        "status": "sent"
      },
      "to": {
        "type": "affiliate",
        "id": "569923c3e07e363c19220290",
        "name": "Agencia de Test",
        "email": "pablo@yourttoo.com",
        "avatarimg": "http://res.cloudinary.com/openmarket-travel/image/upload/cs_no_cmyk/w_36,h_36,c_fill,g_face,q_90,r_18/hrh92ko7prbyxml4hcat.jpg",
        "status": "read"
      },
      "showTranslation": false
    },
    {
      "message": "---.----&gt; AAVV to DMC 19 9",
      "date": "2016-02-09T18:09:52.925Z",
      "_id": "56ba2b07eff6fdb4157a766f",
      "from": {
        "type": "affiliate",
        "id": "569923c3e07e363c19220290",
        "name": "Agencia de Test",
        "email": "pablo@yourttoo.com",
        "avatarimg": "http://res.cloudinary.com/openmarket-travel/image/upload/cs_no_cmyk/w_36,h_36,c_fill,g_face,q_90,r_18/hrh92ko7prbyxml4hcat.jpg",
        "status": "read"
      },
      "to": {
        "type": "dmc",
        "id": "547f280c7584bc040ff2c606",
        "name": "Dmc Test Ltd",
        "email": "pableco@gmail.com",
        "avatarimg": "http://res.cloudinary.com/open-market-travel/image/upload/cs_no_cmyk/w_36,h_36,c_fill,g_face,q_90,r_18/kfnorwwnumnxxhk42tv1.png",
        "status": "read"
      }
    },
    {
      "message": "&lt;------- DMC to AAVV 19 11",
      "date": "2016-02-09T18:11:13.779Z",
      "_id": "56ba2b570392112412979ed5",
      "from": {
        "type": "dmc",
        "id": "547f280c7584bc040ff2c606",
        "name": "Dmc Test Ltd",
        "email": "pableco@gmail.com",
        "avatarimg": "http://res.cloudinary.com/open-market-travel/image/upload/cs_no_cmyk/w_36,h_36,c_fill,g_face,q_90,r_18/kfnorwwnumnxxhk42tv1.png",
        "status": "sent"
      },
      "to": {
        "type": "affiliate",
        "id": "569923c3e07e363c19220290",
        "name": "Agencia de Test",
        "email": "pablo@yourttoo.com",
        "avatarimg": "http://res.cloudinary.com/openmarket-travel/image/upload/cs_no_cmyk/w_36,h_36,c_fill,g_face,q_90,r_18/hrh92ko7prbyxml4hcat.jpg",
        "status": "read"
      },
      "showTranslation": false
    },
    {
      "message": "dmc to affilate 1",
      "date": "2016-02-11T13:18:22.842Z",
      "_id": "56bc8a0ff422cce03130dd5b",
      "from": {
        "type": "dmc",
        "id": "547f280c7584bc040ff2c606",
        "name": "Dmc Test Ltd",
        "email": "pableco@gmail.com",
        "avatarimg": "http://res.cloudinary.com/open-market-travel/image/upload/cs_no_cmyk/w_36,h_36,c_fill,g_face,q_90,r_18/kfnorwwnumnxxhk42tv1.png",
        "status": "read"
      },
      "to": {
        "type": "affiliate",
        "id": "569923c3e07e363c19220290",
        "name": "Agencia de Test",
        "email": "pablo@yourttoo.com",
        "avatarimg": "http://res.cloudinary.com/openmarket-travel/image/upload/cs_no_cmyk/w_36,h_36,c_fill,g_face,q_90,r_18/hrh92ko7prbyxml4hcat.jpg",
        "status": "read"
      },
      "showTranslation": false
    },
    {
      "message": "DMC para AAVV 14 37",
      "date": "2016-02-11T13:37:23.092Z",
      "_id": "56bc8e31e126e70011e33c68",
      "from": {
        "type": "dmc",
        "id": "547f280c7584bc040ff2c606",
        "name": "Dmc Test Ltd",
        "email": "pableco@gmail.com",
        "avatarimg": "http://res.cloudinary.com/open-market-travel/image/upload/cs_no_cmyk/w_36,h_36,c_fill,g_face,q_90,r_18/kfnorwwnumnxxhk42tv1.png",
        "status": "sent"
      },
      "to": {
        "type": "affiliate",
        "id": "569923c3e07e363c19220290",
        "name": "Agencia de Test",
        "email": "pablo@yourttoo.com",
        "avatarimg": "http://res.cloudinary.com/openmarket-travel/image/upload/cs_no_cmyk/w_36,h_36,c_fill,g_face,q_90,r_18/hrh92ko7prbyxml4hcat.jpg",
        "status": "read"
      },
      "showTranslation": false
    },
    {
      "message": "Afiliado a agencia",
      "date": "2016-03-02T08:05:17.580Z",
      "_id": "56d69e4be0af6df84d413a4f",
      "from": {
        "type": "affiliate",
        "id": "569923c3e07e363c19220290",
        "name": "Agencia de Test",
        "email": "pablo@yourttoo.com",
        "avatarimg": "http://res.cloudinary.com/openmarket-travel/image/upload/cs_no_cmyk/w_36,h_36,c_fill,g_face,q_90,r_18/hrh92ko7prbyxml4hcat.jpg",
        "status": "read"
      },
      "to": {
        "type": "dmc",
        "id": "547f280c7584bc040ff2c606",
        "name": "Dmc Test Ltd",
        "email": "pableco@gmail.com",
        "avatarimg": "http://res.cloudinary.com/open-market-travel/image/upload/cs_no_cmyk/w_36,h_36,c_fill,g_face,q_90,r_18/kfnorwwnumnxxhk42tv1.png",
        "status": "read"
      }
    },
    {
      "message": "respondo azul",
      "date": "2016-03-02T08:31:52.661Z",
      "_id": "56d6a48697b16120647cb9dd",
      "from": {
        "type": "affiliate",
        "id": "569923c3e07e363c19220290",
        "name": "Agencia de Test",
        "email": "pablo@yourttoo.com",
        "avatarimg": "http://res.cloudinary.com/openmarket-travel/image/upload/cs_no_cmyk/w_36,h_36,c_fill,g_face,q_90,r_18/hrh92ko7prbyxml4hcat.jpg",
        "status": "sent"
      },
      "to": {
        "type": "dmc",
        "id": "547f280c7584bc040ff2c606",
        "name": "Dmc Test Ltd",
        "email": "pableco@gmail.com",
        "avatarimg": "http://res.cloudinary.com/open-market-travel/image/upload/cs_no_cmyk/w_36,h_36,c_fill,g_face,q_90,r_18/kfnorwwnumnxxhk42tv1.png",
        "status": "read"
      }
    },
    {
      "message": "Mensaje 10 44 FF",
      "date": "2016-03-02T09:44:50.411Z",
      "_id": "56d6b5a097b16120647cb9df",
      "from": {
        "type": "affiliate",
        "id": "569923c3e07e363c19220290",
        "name": "Agencia de Test",
        "email": "pablo@yourttoo.com",
        "avatarimg": "http://res.cloudinary.com/openmarket-travel/image/upload/cs_no_cmyk/w_36,h_36,c_fill,g_face,q_90,r_18/hrh92ko7prbyxml4hcat.jpg",
        "status": "sent"
      },
      "to": {
        "type": "dmc",
        "id": "547f280c7584bc040ff2c606",
        "name": "Dmc Test Ltd",
        "email": "pableco@gmail.com",
        "avatarimg": "http://res.cloudinary.com/open-market-travel/image/upload/cs_no_cmyk/w_36,h_36,c_fill,g_face,q_90,r_18/kfnorwwnumnxxhk42tv1.png",
        "status": "new"
      }
    },
    {
      "message": "probando desde admin dmc",
      "date": "2016-03-02T10:31:02.408Z",
      "_id": "56d6c07597b16120647cb9e1",
      "from": {
        "type": "admin",
        "id": "547f0080260ed5c409def5f4",
        "name": "Pablo",
        "email": "pablo@openmarket.travel",
        "avatarimg": "http://res.cloudinary.com/open-market-travel/image/upload/cs_no_cmyk/w_36,h_36,c_fill,g_face,q_90,r_18/avatar.jpg",
        "status": "sent"
      },
      "to": {
        "type": "dmc",
        "id": "547f280c7584bc040ff2c606",
        "name": "Dmc Test Ltd",
        "email": "pableco@gmail.com",
        "avatarimg": "http://res.cloudinary.com/open-market-travel/image/upload/cs_no_cmyk/w_36,h_36,c_fill,g_face,q_90,r_18/kfnorwwnumnxxhk42tv1.png",
        "status": "new"
      },
      "showTranslation": false
    },
    {
      "message": "test",
      "date": "2016-03-02T10:38:09.522Z",
      "_id": "56d6c220f1a76ae85a883a59",
      "from": {
        "type": "admin",
        "id": "547f0080260ed5c409def5f4",
        "name": "Pablo",
        "email": "pablo@openmarket.travel",
        "avatarimg": "http://res.cloudinary.com/open-market-travel/image/upload/cs_no_cmyk/w_36,h_36,c_fill,g_face,q_90,r_18/avatar.jpg",
        "status": "sent"
      },
      "to": {
        "type": "dmc",
        "id": "547f280c7584bc040ff2c606",
        "name": "Dmc Test Ltd",
        "email": "pableco@gmail.com",
        "avatarimg": "http://res.cloudinary.com/open-market-travel/image/upload/cs_no_cmyk/w_36,h_36,c_fill,g_face,q_90,r_18/kfnorwwnumnxxhk42tv1.png"
      },
      "showTranslation": false
    },
    {
      "message": "desde afiliado mando a es11 dmc test",
      "date": "2016-03-02T10:56:41.077Z",
      "_id": "56d6c6793b3fe84c5d40beb7",
      "from": {
        "type": "affiliate",
        "id": "569923c3e07e363c19220290",
        "name": "Agencia de Test",
        "email": "pablo@yourttoo.com",
        "avatarimg": "http://res.cloudinary.com/openmarket-travel/image/upload/cs_no_cmyk/w_36,h_36,c_fill,g_face,q_90,r_18/hrh92ko7prbyxml4hcat.jpg",
        "status": "sent"
      },
      "to": {
        "type": "dmc",
        "id": "547f280c7584bc040ff2c606",
        "name": "Dmc Test Ltd",
        "email": "pableco@gmail.com",
        "avatarimg": "http://res.cloudinary.com/open-market-travel/image/upload/cs_no_cmyk/w_36,h_36,c_fill,g_face,q_90,r_18/kfnorwwnumnxxhk42tv1.png",
        "status": "new"
      }
    }
  ]
}